wavestate/collection/__init__.py
wavestate/collection/_version.py
wavestate-0.0.1.dist-info/METADATA
wavestate-0.0.1.dist-info/NOTICE
wavestate-0.0.1.dist-info/WHEEL
wavestate-0.0.1.dist-info/top_level.txt
wavestate-0.0.1.dist-info/RECORD
